Workbook

Sheet Resumen Ejecutivo
A2: ID | B2: Concepto de Gasto | C2: Monto Total (USD) | D2: % del Total
A3: 1.0 | B3: Costos Directos de Personal (Honorarios Profesionales) | C3: ='Costos Directos de Personal'!E8 -> 48000 | D3: =C3/$C$7 -> 0.85207302
A4: 2.0 | B4: Costos de Infraestructura Cloud y Licenciamiento | C4: ='Costos de Infraestructura Cloud'!F11 -> 3212 | D4: =C4/$C$7 -> 0.057017886
A5: 3.0 | B5: Gastos Administrativos / Overhead (5%) [1] | C5: =(C3+C4)*5% -> 2560.6 | D5: =C5/$C$7 -> 0.045454545
A6: 4.0 | B6: Reserva de Contingencia de Gestión (5%) [2] | C6: =(C3+C4)*5% -> 2560.6 | D6: =C6/$C$7 -> 0.045454545
B7: PRESUPUESTO TOTAL (SUMA ALZADA) | C7: =SUM(C3:C6) -> 56333.2 | D7: =SUM(D3:D6) -> 1
A10: Notas Financieras: [1] Overhead: Cubre costos de facturación, representaciones legales y gastos de back-office de la firma consultora. [2] Contingencia: Administrada por el Project Manager para absorber fluctuaciones en el costo de la nube por variaciones de la tasa de cambio o picos de procesamiento imprevistos. Si no se usa, incrementa el margen de utilidad.

Sheet Costos Directos de Personal
A2: Basado en un calendario de 20 días laborables por mes (80 días total). Las tarifas reflejan el nivel Seniority requerido para procesar datos de salud pública a nivel nacional.
A3: Rol del Consultor | B3: Tipo de Contratación | C3: Tarifa Diaria (USD) | D3: Días Asignados | E3: Total (USD) | F3: Justificación del Nivel de Esfuerzo (LOE)
A4: Lead Data Engineer / Cloud Architect | B4: Consultor Core (Key Personnel) | C4: 300 | D4: 80 | E4: =C4*D4 -> 24000 | F4: Responsable de la infraestructura AWS, diseño del Data Warehouse, y programación de pipelines ETL (Glue/Python).
A5: Lead Data Scientist / BI Expert | B5: Consultor Core (Key Personnel) | C5: 250 | D5: 80 | E5: =C5*D5 -> 20000 | F5: Desarrollo del modelo predictivo (ML), análisis estadístico Pre/Post COVID y creación de visualizaciones en Power BI/Tableau.
A6: Project Manager (PMP) | B6: Contratación / Soporte | C6: 150 | D6: 16 | E6: =C6*D6 -> 2400 | F6: 1 día semanal. Control del WBS, gestión de riesgos, QA, informes de avance y enlace directo con Patrocinadores.
A7: Epidemiólogo (SME) | B7: Contratación / Soporte | C7: 200 | D7: 8 | E7: =C7*D7 -> 1600 | F7: Auditoría clínica del cruce de códigos CIE-10 y validación de hallazgos del impacto en enfermedades crónicas.
A8: TOTAL PERSONAL | D8: =SUM(D4:D7) -> 184 | E8: =SUM(E4:E7) -> 48000

Sheet Costos de Infraestructura Cloud
A2: Presupuesto dimensionado para entornos de Producción (Enterprise-grade). Se excluye explícitamente el uso de "Free Tiers" para garantizar el cumplimiento de los Service Level Agreements (SLA) del 99.9% exigidos por Gobierno.
A3: Categoría | B3: Servicio / Proveedor | C3: Especificación Técnica | D3: Costo Mensual (USD) | E3: Meses | F3: Total (USD)
A4: Database | B4: AWS RDS PostgreSQL | C4: Instancia Multi-AZ (Alta Disponibilidad), db.t3.large, 100GB disco SSD gp3, Backups automáticos 7 días. | D4: 235 | E4: 4 | F4: =D4*E4 -> 940
A5: Compute / ETL | B5: AWS Glue (Serverless) | C5: Ejecución de 5 Jobs diarios. Consumo estimado: 2 DPUs * 1.5 horas/día * 30 días * $0.44/DPU-hora. | D5: 198 | E5: 4 | F5: =D5*E5 -> 792
A6: Storage & Sec | B6: AWS S3 + Secrets Mgr | C6: Almacenamiento RAW Data en S3 Standard + 5 Secretos rotados + Logs de auditoría en CloudWatch. | D6: 50 | E6: 4 | F6: =D6*E6 -> 200
A7: Redes / Egress | B7: AWS Data Transfer Out | C7: Tráfico estimado de salida hacia Power BI Service (50 GB/mes). | D7: 20 | E7: 4 | F7: =D7*E7 -> 80
A8: Licencias BI | B8: Power BI Pro | C8: 5 Licencias (2 Consultores + 3 Usuarios Clave MSPAS/PNUD) a $10 c/u para publicación de reportes en Workspace privado. | D8: 50 | E8: 4 | F8: =D8*E8 -> 200
A9: Licencias GIS | B9: Tableau Creator | C9: 2 Licencias ($75 c/u) para desarrollo de mapas coropléticos departamentales de saturación hospitalaria. | D9: 150 | E9: 4 | F9: =D9*E9 -> 600
A10: Repositorio | B10: GitHub Enterprise | C10: Plan Team. Incluye GitHub Actions para CI/CD continuo (compilación y despliegue del sitio web MkDocs). | D10: 100 | E10: 4 | F10: =D10*E10 -> 400
A11: TOTAL INFRA. | F11: =SUM(F4:F10) -> 3212

Sheet Calendario de Desembolsos (Hito
A2: Pago | B2: Correspondencia WBS | C2: Hito de Entrega (Milestone) | D2: Condición de Aprobación | E2: % | F2: Monto a Facturar (USD)
A3: Pago 1 | B3: Fase 1.0 | C3: Diseño y Gobernanza Aprobados. (Fin Mes 1). Entrega de Project Charter, WBS, Matriz RACI, Diagramas de Arquitectura (Draw.io) y Modelado ERD. | D3: Firma de Patrocinador en Documento de Diseño. | E3: 0.2 | F3: =E3*'Resumen Ejecutivo'!$C$7 -> 11266.64
A4: Pago 2 | B4: Fase 2.0 | C4: Infraestructura Cloud y Data Warehouse Desplegados. (Fin Mes 2). Scripts de ingesta corriendo y DB PostgreSQL poblada en esquema Stage/DW. | D4: Demo técnica exitosa y revisión de código en GitHub. | E4: 0.3 | F4: =E4*'Resumen Ejecutivo'!$C$7 -> 16899.96
A5: Pago 3 | B5: Fase 3.0 | C5: Capa Analítica y Modelado ML. (Fin Mes 3). 4 Dashboards funcionales y modelo de Machine Learning (.tar) exportado con evaluación de precisión. | D5: Validación clínica del SME y validación visual PNUD. | E5: 0.3 | F5: =E5*'Resumen Ejecutivo'!$C$7 -> 16899.96
A6: Pago 4 | B6: Fase 4.0 | C6: Cierre, Documentación y Handover. (Fin Mes 4). Informe Consultivo Final, Portal MkDocs desplegado y Taller de Capacitación impartido al MSPAS. | D6: Acta de Aceptación Final y Entrega de Llaves AWS. | E6: 0.2 | F6: =E6*'Resumen Ejecutivo'!$C$7 -> 11266.64
D7: TOTAL CONTRATO | E7: =SUM(E3:E6) -> 1 | F7: =SUM(F3:F6) -> 56333.2
